README.md
setup.py
joke_generator/__init__.py
joke_generator/joke_generator.py
joke_generator.egg-info/PKG-INFO
joke_generator.egg-info/SOURCES.txt
joke_generator.egg-info/dependency_links.txt
joke_generator.egg-info/requires.txt
joke_generator.egg-info/top_level.txt