Metadata-Version: 2.1
Name: joke-generator
Version: 1.0.1
Summary: Returns a random joke
Home-page: https://github.com/dewittethomas/joke-generator
Author: Thomas Dewitte
Author-email: thomasdewittecontact@gmail.com
License: MIT
Platform: UNKNOWN
Classifier: Development Status :: 5 - Production/Stable
Classifier: License :: OSI Approved :: MIT License
Classifier: Operating System :: OS Independent
Classifier: Programming Language :: Python :: 3
Requires-Python: >= 3.5
